hello/__init__.py
hello/hello.py
chris_testing_versioning_stuff-2.0.0.dist-info/METADATA
chris_testing_versioning_stuff-2.0.0.dist-info/WHEEL
chris_testing_versioning_stuff-2.0.0.dist-info/top_level.txt
chris_testing_versioning_stuff-2.0.0.dist-info/RECORD
