Metadata-Version: 2.2
Name: chris-testing-versioning-stuff
Version: 2.0.0
Summary: Add your description here
License: Apache 2.0
Requires-Python: >=3.11
